somnon/__init__.py
somnon-0.1.5.dist-info/LICENSE.rst
somnon-0.1.5.dist-info/METADATA
somnon-0.1.5.dist-info/WHEEL
somnon-0.1.5.dist-info/top_level.txt
somnon-0.1.5.dist-info/RECORD
