Metadata-Version: 2.1
Name: somnon
Version: 0.1.5
Summary: Rust-like Option and Result implementation
Author-email: Eemil Kiviahde <eemil.kiviahde@coldheart.dev>
License: GNU GENERAL PUBLIC LICENSE
Project-URL: github, https://github.com/coldhearti/somnon
Requires-Python: >=3.11
License-File: LICENSE.rst
